fineslice/__init__.py
fineslice/affine.py
fineslice/bounds.py
fineslice/cuboid.py
fineslice/debug_utils.py
fineslice/intersect.py
fineslice/sampler_0d.py
fineslice/sampler_1d.py
fineslice/sampler_2d.py
fineslice/sampler_3d.py
fineslice/types.py
fineslice/utils.py
fineslice-0.0.3.dist-info/LICENSE
fineslice-0.0.3.dist-info/METADATA
fineslice-0.0.3.dist-info/WHEEL
fineslice-0.0.3.dist-info/RECORD
