Metadata-Version: 2.1
Name: fineslice
Version: 0.0.3
Summary: Affine slicer.
License: BSD 3-Clause License
Author: Florian Rupprecht
Author-email: floruppr@gmail.com
Requires-Python: >=3.9
Classifier: License :: Other/Proprietary License
Classifier: Programming Language :: Python :: 3
Classifier: Programming Language :: Python :: 3.9
Classifier: Programming Language :: Python :: 3.10
Classifier: Programming Language :: Python :: 3.11
Classifier: Programming Language :: Python :: 3.12
Requires-Dist: numpy (>=1.21.2,<2.0.0)
